phoneinfopy/__init__.py
phoneinfopy/cli.py
phoneinfopy-1.0.0.17.dist-info/METADATA
phoneinfopy-1.0.0.17.dist-info/WHEEL
phoneinfopy-1.0.0.17.dist-info/top_level.txt
phoneinfopy-1.0.0.17.dist-info/RECORD
