Metadata-Version: 2.1
Name: phoneinfopy
Version: 1.0.0.17
Summary: phoneinfopy is a Python package that allow you to get respones from truecaller APIs. You can able to do login, OTP verification, and phone number search using Truecaller API with this package.
Author: Mr_3rr0r_501 [yuvaraj]
Author-email: <yuvarajucet@gmail.com>
Keywords: truecaller,phoneinfo,numberinfo,phonenumberinfo
Classifier: Topic :: Utilities
Classifier: Natural Language :: English
Classifier: Operating System :: OS Independent
Classifier: Programming Language :: Python :: 3
Requires-Dist: requests
